{"Count":147,"Message":"Response returned successfully","SearchCriteria":"Vehicle Type: car","Results":[{"MakeId":440,"MakeName":"Aston Martin","VehicleTypeId":2,"VehicleTypeName":"Passenger Car"},{"MakeId":441,"MakeName":"Tesla","VehicleTypeId":2,"VehicleTypeName":"Passenger Car"},{"MakeId":442,"MakeName":"Jaguar","VehicleTypeId":2,"VehicleTypeName":"Passenger Car"},{"MakeId":443,"MakeName":"Maserati","VehicleTypeId":2,"VehicleTypeName":"Passenger Car"},{"MakeId":445,"MakeName":"Rolls Royce","VehicleTypeId":2,"VehicleTypeName":"Passenger Car"},{"MakeId":448,"MakeName":"Toyota","VehicleTypeId":2,"VehicleTypeName":"Passenger Car"},{"MakeId":449,"MakeName":"Mercedes-Benz","VehicleTypeId":2,"VehicleTypeName":"Passenger Car"},{"MakeId":452,"MakeName":"BMW","VehicleTypeId":2,"VehicleTypeName":"Passenger Car"},{"MakeId":454,"MakeName":"Bugatti","VehicleTypeId":2,"VehicleTypeName":"Passenger Car"},{"MakeId":456,"MakeName":"MINI","VehicleTypeId":2,"VehicleTypeName":"Passenger Car"},{"MakeId":460,"MakeName":"Ford","VehicleTypeId":2,"VehicleTypeName":"Passenger Car"},{"MakeId":464,"MakeName":"Lincoln","VehicleTypeId":2,"VehicleTypeName":"Passenger Car"},{"MakeId":465,"MakeName":"Mercury","VehicleTypeId":2,"VehicleTypeName":"Passenger Car"},{"MakeId":466,"MakeName":"Lotus","VehicleTypeId":2,"VehicleTypeName":"Passenger Car"},{"MakeId":467,"MakeName":"Chevrolet","VehicleTypeId":2,"VehicleTypeName":"Passenger Car"},{"MakeId":468,"MakeName":"Buick","VehicleTypeId":2,"VehicleTypeName":"Passenger Car"},{"MakeId":469,"MakeName":"Cadillac","VehicleTypeId":2,"VehicleTypeName":"Passenger Car"},{"MakeId":470,"MakeName":"Holden","VehicleTypeId":2,"VehicleTypeName":"Passenger Car"},{"MakeId":471,"MakeName":"Opel","VehicleTypeId":2,"VehicleTypeName":"Passenger Car"},{"MakeId":472,"MakeName":"GMC","VehicleTypeId":2,"VehicleTypeName":"Passenger Car"},{"MakeId":473,"MakeName":"Mazda","VehicleTypeId":2,"VehicleTypeName":"Passenger Car"},{"MakeId":474,"MakeName":"Honda","VehicleTypeId":2,"VehicleTypeName":"Passenger Car"},{"MakeId":475,"MakeName":"Acura","VehicleTypeId":2,"VehicleTypeName":"Passenger Car"},{"MakeId":476,"MakeName":"Dodge","VehicleTypeId":2,"VehicleTypeName":"Passenger Car"},{"MakeId":477,"MakeName":"Chrysler","VehicleTypeId":2,"VehicleTypeName":"Passenger Car"},{"MakeId":478,"MakeName":"Nissan","VehicleTypeId":2,"VehicleTypeName":"Passenger Car"},{"MakeId":480,"MakeName":"Infiniti","VehicleTypeId":2,"VehicleTypeName":"Passenger Car"},{"MakeId":481,"MakeName":"Mitsubishi","VehicleTypeId":2,"VehicleTypeName":"Passenger Car"},{"MakeId":482,"MakeName":"Volkswagen","VehicleTypeId":2,"VehicleTypeName":"Passenger Car"},{"MakeId":485,"MakeName":"Volvo","VehicleTypeId":2,"VehicleTypeName":"Passenger Car"},{"MakeId":492,"MakeName":"Fiat","VehicleTypeId":2,"VehicleTypeName":"Passenger Car"},{"MakeId":493,"MakeName":"Alfa Romeo","VehicleTypeId":2,"VehicleTypeName":"Passenger Car"},{"MakeId":497,"MakeName":"Lancia","VehicleTypeId":2,"VehicleTypeName":"Passenger Car"},{"MakeId":498,"MakeName":"Hyundai","VehicleTypeId":2,"VehicleTypeName":"Passenger Car"},{"MakeId":499,"MakeName":"Kia","VehicleTypeId":2,"VehicleTypeName":"Passenger Car"},{"MakeId":502,"MakeName":"Lamborghini","VehicleTypeId":2,"VehicleTypeName":"Passenger Car"},{"MakeId":504,"MakeName":"smart","VehicleTypeId":2,"VehicleTypeName":"Passenger Car"},{"MakeId":509,"MakeName":"Suzuki","VehicleTypeId":2,"VehicleTypeName":"Passenger Car"},{"MakeId":515,"MakeName":"Lexus","VehicleTypeId":2,"VehicleTypeName":"Passenger Car"},{"MakeId":523,"MakeName":"Subaru","VehicleTypeId":2,"VehicleTypeName":"Passenger Car"},{"MakeId":533,"MakeName":"Maybach","VehicleTypeId":2,"VehicleTypeName":"Passenger Car"},{"MakeId":536,"MakeName":"Pontiac","VehicleTypeId":2,"VehicleTypeName":"Passenger Car"},{"MakeId":539,"MakeName":"Morgan Motor","VehicleTypeId":2,"VehicleTypeName":"Passenger Car"},{"MakeId":542,"MakeName":"Isuzu","VehicleTypeId":2,"VehicleTypeName":"Passenger Car"},{"MakeId":572,"MakeName":"SAAB","VehicleTypeId":2,"VehicleTypeName":"Passenger Car"},{"MakeId":582,"MakeName":"Audi","VehicleTypeId":2,"VehicleTypeName":"Passenger Car"},{"MakeId":583,"MakeName":"Bentley","VehicleTypeId":2,"VehicleTypeName":"Passenger Car"},{"MakeId":584,"MakeName":"Porsche","VehicleTypeId":2,"VehicleTypeName":"Passenger Car"},{"MakeId":603,"MakeName":"Ferrari","VehicleTypeId":2,"VehicleTypeName":"Passenger Car"},{"MakeId":606,"MakeName":"AM General","VehicleTypeId":2,"VehicleTypeName":"Passenger Car"},{"MakeId":629,"MakeName":"Creative Coachworks","VehicleTypeId":2,"VehicleTypeName":"Passenger Car"},{"MakeId":667,"MakeName":"D & N Trailers","VehicleTypeId":2,"VehicleTypeName":"Passenger Car"},{"MakeId":847,"MakeName":"Daihatsu","VehicleTypeId":2,"VehicleTypeName":"Passenger Car"},{"MakeId":972,"MakeName":"Falcon","VehicleTypeId":2,"VehicleTypeName":"Passenger Car"},{"MakeId":986,"MakeName":"EV Innovations","VehicleTypeId":2,"VehicleTypeName":"Passenger Car"},{"MakeId":992,"MakeName":"Faw Jiaxing Happy Messenger","VehicleTypeId":2,"VehicleTypeName":"Passenger Car"},{"MakeId":1033,"MakeName":"FISKER AUTOMOTIVE","VehicleTypeId":2,"VehicleTypeName":"Passenger Car"},{"MakeId":1034,"MakeName":"Nina","VehicleTypeId":2,"VehicleTypeName":"Passenger Car"},{"MakeId":1056,"MakeName":"Saturn","VehicleTypeId":2,"VehicleTypeName":"Passenger Car"},{"MakeId":1075,"MakeName":"GMNA (Opel & Daewoo)","VehicleTypeId":2,"VehicleTypeName":"Passenger Car"},{"MakeId":1077,"MakeName":"Daewoo","VehicleTypeId":2,"VehicleTypeName":"Passenger Car"},{"MakeId":1104,"MakeName":"BYD Auto","VehicleTypeId":2,"VehicleTypeName":"Passenger Car"},{"MakeId":1142,"MakeName":"Formula 1 Street Com","VehicleTypeId":2,"VehicleTypeName":"Passenger Car"},{"MakeId":1146,"MakeName":"Geo","VehicleTypeId":2,"VehicleTypeName":"Passenger Car"},{"MakeId":1151,"MakeName":"FortuneSport VES","VehicleTypeId":2,"VehicleTypeName":"Passenger Car"},{"MakeId":1288,"MakeName":"Alan Autosports","VehicleTypeId":2,"VehicleTypeName":"Passenger Car"},{"MakeId":1292,"MakeName":"EQUUS AUTOMOTIVE","VehicleTypeId":2,"VehicleTypeName":"Passenger Car"},{"MakeId":1393,"MakeName":"Electric Mobile Cars","VehicleTypeId":2,"VehicleTypeName":"Passenger Car"},{"MakeId":1498,"MakeName":"Avera Motors","VehicleTypeId":2,"VehicleTypeName":"Passenger Car"},{"MakeId":1532,"MakeName":"GREENTECH AUTOMOTIVE","VehicleTypeId":2,"VehicleTypeName":"Passenger Car"},{"MakeId":1569,"MakeName":"GM","VehicleTypeId":2,"VehicleTypeName":"Passenger Car"},{"MakeId":1683,"MakeName":"Bakkura Mobility","VehicleTypeId":2,"VehicleTypeName":"Passenger Car"},{"MakeId":1755,"MakeName":"Th!nk","VehicleTypeId":2,"VehicleTypeName":"Passenger Car"},{"MakeId":1824,"MakeName":"COMMUNITY CARS ","VehicleTypeId":2,"VehicleTypeName":"Passenger Car"},{"MakeId":1869,"MakeName":"CONTEMPORARY CLASSIC CARS","VehicleTypeId":2,"VehicleTypeName":"Passenger Car"},{"MakeId":1896,"MakeName":"Koenigsegg Automotive","VehicleTypeId":2,"VehicleTypeName":"Passenger Car"},{"MakeId":1999,"MakeName":"Changzhou Greenland Vehicle Co., Ltd.","VehicleTypeId":2,"VehicleTypeName":"Passenger Car"},{"MakeId":2049,"MakeName":"Kepler Motors","VehicleTypeId":2,"VehicleTypeName":"Passenger Car"},{"MakeId":2236,"MakeName":"Mclaren","VehicleTypeId":2,"VehicleTypeName":"Passenger Car"},{"MakeId":2376,"MakeName":"mycar","VehicleTypeId":2,"VehicleTypeName":"Passenger Car"},{"MakeId":2408,"MakeName":"Eagle","VehicleTypeId":2,"VehicleTypeName":"Passenger Car"},{"MakeId":2409,"MakeName":"Plymouth","VehicleTypeId":2,"VehicleTypeName":"Passenger Car"},{"MakeId":2618,"MakeName":"Nanchang Freedom Technology Limited Company ","VehicleTypeId":2,"VehicleTypeName":"Passenger Car"},{"MakeId":2745,"MakeName":"Phoenix Motorcars","VehicleTypeId":2,"VehicleTypeName":"Passenger Car"},{"MakeId":2990,"MakeName":"Red Baron Motors","VehicleTypeId":2,"VehicleTypeName":"Passenger Car"},{"MakeId":3027,"MakeName":"Strother Welding","VehicleTypeId":2,"VehicleTypeName":"Passenger Car"},{"MakeId":3176,"MakeName":"Rocket Sled Motors","VehicleTypeId":2,"VehicleTypeName":"Passenger Car"},{"MakeId":3401,"MakeName":"Think Passenger Car","VehicleTypeId":2,"VehicleTypeName":"Passenger Car"},{"MakeId":3440,"MakeName":"Vision Industries","VehicleTypeId":2,"VehicleTypeName":"Passenger Car"},{"MakeId":3540,"MakeName":"Warhawk Performance","VehicleTypeId":2,"VehicleTypeName":"Passenger Car"},{"MakeId":3583,"MakeName":"Ukeycheyma","VehicleTypeId":2,"VehicleTypeName":"Passenger Car"},{"MakeId":3766,"MakeName":"Spyker ","VehicleTypeId":2,"VehicleTypeName":"Passenger Car"},{"MakeId":3803,"MakeName":"Wheego Electric Cars","VehicleTypeId":2,"VehicleTypeName":"Passenger Car"},{"MakeId":4162,"MakeName":"Oldsmobile","VehicleTypeId":2,"VehicleTypeName":"Passenger Car"},{"MakeId":4220,"MakeName":"PANOZ AUTO DEVELOPMENT","VehicleTypeId":2,"VehicleTypeName":"Passenger Car"},{"MakeId":4355,"MakeName":"Saleen","VehicleTypeId":2,"VehicleTypeName":"Passenger Car"},{"MakeId":4410,"MakeName":"Solectria Corporation","VehicleTypeId":2,"VehicleTypeName":"Passenger Car"},{"MakeId":4451,"MakeName":"Yester Year Auto","VehicleTypeId":2,"VehicleTypeName":"Passenger Car"},{"MakeId":4554,"MakeName":"Movitron S.R.L.","VehicleTypeId":2,"VehicleTypeName":"Passenger Car"},{"MakeId":4634,"MakeName":"Engine Connection","VehicleTypeId":2,"VehicleTypeName":"Passenger Car"},{"MakeId":4644,"MakeName":"Bluecar, SAS","VehicleTypeId":2,"VehicleTypeName":"Passenger Car"},{"MakeId":4744,"MakeName":"Xiangrui Vehicle Co.","VehicleTypeId":2,"VehicleTypeName":"Passenger Car"},{"MakeId":4764,"MakeName":"Mosler","VehicleTypeId":2,"VehicleTypeName":"Passenger Car"},{"MakeId":4767,"MakeName":"Pagani","VehicleTypeId":2,"VehicleTypeName":"Passenger Car"},{"MakeId":4859,"MakeName":"Revology","VehicleTypeId":2,"VehicleTypeName":"Passenger Car"},{"MakeId":5015,"MakeName":"eMa","VehicleTypeId":2,"VehicleTypeName":"Passenger Car"},{"MakeId":5042,"MakeName":"Costin sports car","VehicleTypeId":2,"VehicleTypeName":"Passenger Car"},{"MakeId":5083,"MakeName":"Genesis","VehicleTypeId":2,"VehicleTypeName":"Passenger Car"},{"MakeId":5122,"MakeName":"KARMA","VehicleTypeId":2,"VehicleTypeName":"Passenger Car"},{"MakeId":5208,"MakeName":"Matrix Motor Company","VehicleTypeId":2,"VehicleTypeName":"Passenger Car"},{"MakeId":5367,"MakeName":"Armbruster Stageway ","VehicleTypeId":2,"VehicleTypeName":"Passenger Car"},{"MakeId":5381,"MakeName":"Lumen","VehicleTypeId":2,"VehicleTypeName":"Passenger Car"},{"MakeId":5464,"MakeName":"Asuna","VehicleTypeId":2,"VehicleTypeName":"Passenger Car"},{"MakeId":5468,"MakeName":"MERKUR","VehicleTypeId":2,"VehicleTypeName":"Passenger Car"},{"MakeId":5476,"MakeName":"Continental","VehicleTypeId":2,"VehicleTypeName":"Passenger Car"},{"MakeId":5552,"MakeName":"Avanti Motors","VehicleTypeId":2,"VehicleTypeName":"Passenger Car"},{"MakeId":5553,"MakeName":"YUGO","VehicleTypeId":2,"VehicleTypeName":"Passenger Car"},{"MakeId":5554,"MakeName":"Peugeot","VehicleTypeId":2,"VehicleTypeName":"Passenger Car"},{"MakeId":5555,"MakeName":"Sterling Motor Car","VehicleTypeId":2,"VehicleTypeName":"Passenger Car"},{"MakeId":5557,"MakeName":"Consulier","VehicleTypeId":2,"VehicleTypeName":"Passenger Car"},{"MakeId":5657,"MakeName":"Datsun","VehicleTypeId":2,"VehicleTypeName":"Passenger Car"},{"MakeId":5661,"MakeName":"Pininfarina","VehicleTypeId":2,"VehicleTypeName":"Passenger Car"},{"MakeId":5663,"MakeName":"Triumph Motors","VehicleTypeId":2,"VehicleTypeName":"Passenger Car"},{"MakeId":5760,"MakeName":"Vintage Auto ","VehicleTypeId":2,"VehicleTypeName":"Passenger Car"},{"MakeId":5767,"MakeName":"LondonCoach Inc","VehicleTypeId":2,"VehicleTypeName":"Passenger Car"},{"MakeId":5848,"MakeName":"MGS Grand Sport","VehicleTypeId":2,"VehicleTypeName":"Passenger Car"},{"MakeId":5938,"MakeName":"Panther","VehicleTypeId":2,"VehicleTypeName":"Passenger Car"},{"MakeId":6018,"MakeName":"Daytona Coach Builders","VehicleTypeId":2,"VehicleTypeName":"Passenger Car"},{"MakeId":6069,"MakeName":"UCC","VehicleTypeId":2,"VehicleTypeName":"Passenger Car"},{"MakeId":6263,"MakeName":"RS Spider","VehicleTypeId":2,"VehicleTypeName":"Passenger Car"},{"MakeId":6264,"MakeName":"Gruppe B","VehicleTypeId":2,"VehicleTypeName":"Passenger Car"},{"MakeId":6313,"MakeName":"Renaissance","VehicleTypeId":2,"VehicleTypeName":"Passenger Car"},{"MakeId":6364,"MakeName":"Jac 427","VehicleTypeId":2,"VehicleTypeName":"Passenger Car"},{"MakeId":6408,"MakeName":"HUNTER DESIGN GROUP, LLC","VehicleTypeId":2,"VehicleTypeName":"Passenger Car"},{"MakeId":6473,"MakeName":" BLACKWATER  ","VehicleTypeId":2,"VehicleTypeName":"Passenger Car"},{"MakeId":6663,"MakeName":"GULLWING INTERNATIONAL MOTORS, LTD.","VehicleTypeId":2,"VehicleTypeName":"Passenger Car"},{"MakeId":6759,"MakeName":"AMERITECH CORPORATION","VehicleTypeId":2,"VehicleTypeName":"Passenger Car"},{"MakeId":6792,"MakeName":"Stanford Customs","VehicleTypeId":2,"VehicleTypeName":"Passenger Car"},{"MakeId":6880,"MakeName":"CLASSIC ROADSTERS, LTD","VehicleTypeId":2,"VehicleTypeName":"Passenger Car"},{"MakeId":7099,"MakeName":"Cobra Cars","VehicleTypeId":2,"VehicleTypeName":"Passenger Car"},{"MakeId":7207,"MakeName":"C-R CHEETAH RACE CARS","VehicleTypeId":2,"VehicleTypeName":"Passenger Car"},{"MakeId":7225,"MakeName":"PAS","VehicleTypeId":2,"VehicleTypeName":"Passenger Car"},{"MakeId":7425,"MakeName":"Bug Motors","VehicleTypeId":2,"VehicleTypeName":"Passenger Car"},{"MakeId":7765,"MakeName":"Ives Motors Corporation (IMC)","VehicleTypeId":2,"VehicleTypeName":"Passenger Car"},{"MakeId":7836,"MakeName":"Autodelta USA Inc","VehicleTypeId":2,"VehicleTypeName":"Passenger Car"},{"MakeId":8395,"MakeName":"Autocar Ltd","VehicleTypeId":2,"VehicleTypeName":"Passenger Car"},{"MakeId":8605,"MakeName":"BBC","VehicleTypeId":2,"VehicleTypeName":"Passenger Car"}]}